spiderpy/__init__.py
spiderpy/devices/__init__.py
spiderpy/devices/base.py
spiderpy/devices/powerplug.py
spiderpy/devices/thermostat.py
spiderpy/py.typed
spiderpy/spiderapi.py
spiderpy/test_spiderapi.py
spiderpy-1.7.2.dist-info/LICENSE
spiderpy-1.7.2.dist-info/WHEEL
spiderpy-1.7.2.dist-info/METADATA
spiderpy-1.7.2.dist-info/RECORD
