Metadata-Version: 2.1
Name: spiderpy
Version: 1.7.2
Summary: Python wrapper for the Spider API, a way to manage your Spider installation
License: MIT
Author: Peter Nijssen
Author-email: peter@peternijssen.nl
Requires-Python: >=3.8,<4.0
Classifier: License :: OSI Approved :: MIT License
Classifier: Programming Language :: Python :: 3
Classifier: Programming Language :: Python :: 3.10
Classifier: Programming Language :: Python :: 3.8
Classifier: Programming Language :: Python :: 3.9
Requires-Dist: requests (>=2.26.0,<3.0.0)
